autograders/__init__.py
autograders/grade.py
autograders/utils.py
autograders_lib-0.0.2.dist-info/LICENSE
autograders_lib-0.0.2.dist-info/METADATA
autograders_lib-0.0.2.dist-info/WHEEL
autograders_lib-0.0.2.dist-info/top_level.txt
autograders_lib-0.0.2.dist-info/RECORD
