Metadata-Version: 2.1
Name: autograders-lib
Version: 0.0.2
Summary: Autograders Python3 Library
Home-page: https://github.com/autograders/lib/
Author: Andrés Castellanos
Author-email: andres.cv@galileo.edu
License: MIT
Project-URL: Source, https://github.com/autograders/lib/
Project-URL: Documentation, https://github.com/Autograders/lib/blob/main/README.md
Platform: UNKNOWN
Classifier: License :: OSI Approved :: Apache Software License
Classifier: Programming Language :: Python :: 3
Classifier: Programming Language :: Python :: 3.6
Requires-Python: >=3.6
Requires-Dist: boto3
Requires-Dist: paramiko
